pme/__init__.py
pme/main.py
PyMarkEditor-1.0.dist-info/LICENSE
PyMarkEditor-1.0.dist-info/METADATA
PyMarkEditor-1.0.dist-info/WHEEL
PyMarkEditor-1.0.dist-info/entry_points.txt
PyMarkEditor-1.0.dist-info/top_level.txt
PyMarkEditor-1.0.dist-info/RECORD
