Metadata-Version: 2.1
Name: PyMarkEditor
Version: 1.0
Summary: Python markdown preprocessor
Home-page: https://github.com/Palibrix/PyMarkEditor
Author: Palibrix
Author-email: palibrix@gmail.com
License: 'MIT License'
Classifier: Programming Language :: Python :: 3
Classifier: License :: OSI Approved :: MIT License
Classifier: Operating System :: OS Independent
Requires-Python: >=3.6
License-File: LICENSE
